xaal/__init__.py
xaal/pushbullet/__init__.py
xaal/pushbullet/__main__.py
xaal/pushbullet/dev.py
xaal/pushbullet/test.py
xaal_pushbullet-0.1.2.dist-info/METADATA
xaal_pushbullet-0.1.2.dist-info/WHEEL
xaal_pushbullet-0.1.2.dist-info/top_level.txt
xaal_pushbullet-0.1.2.dist-info/RECORD
